api/Dockerfile.development
api/app/db/__init__.py
api/app/db/crud.py
api/app/db/database.py
api/app/db/models.py
api/app/db/schemas.py
api/app/main.py
api/app/statehandler.py
api/app/static/styles.css
api/app/templates/home.html.j2
api/requirements.txt
powermon/__init__.py
powermon/cli.py
powermon/commands/command.py
powermon/commands/command_definition.py
powermon/commands/reading.py
powermon/commands/reading_definition.py
powermon/commands/result.py
powermon/commands/trigger.py
powermon/configmodel/__init__.py
powermon/configmodel/config_model.py
powermon/configmodel/format_config_model.py
powermon/configmodel/port_config_model.py
powermon/configmodel/trigger_config_model.py
powermon/device.py
powermon/libs/__init__.py
powermon/libs/apicoordinator.py
powermon/libs/config.py
powermon/libs/daemon.py
powermon/libs/errors.py
powermon/libs/mqttbroker.py
powermon/libs/version.py
powermon/locale/en/LC_MESSAGES/powermon.mo
powermon/locale/en/LC_MESSAGES/powermon.po
powermon/outputformats/__init__.py
powermon/outputformats/abstractformat.py
powermon/outputformats/bmsresponse.py
powermon/outputformats/cache.py
powermon/outputformats/hass.py
powermon/outputformats/htmltable.py
powermon/outputformats/json_fmt.py
powermon/outputformats/raw.py
powermon/outputformats/simple.py
powermon/outputformats/table.py
powermon/outputformats/topics.py
powermon/outputs/__init__.py
powermon/outputs/abstractoutput.py
powermon/outputs/api_mqtt.py
powermon/outputs/mqtt.py
powermon/outputs/screen.py
powermon/ports/__init__.py
powermon/ports/abstractport.py
powermon/ports/bleport.py
powermon/ports/serialport.py
powermon/ports/testport.py
powermon/ports/usbport.py
powermon/protocols/__init__.py
powermon/protocols/abstractprotocol.py
powermon/protocols/daly.py
powermon/protocols/docs/DALY-CAN_CommunicationsProtocol_v1.0.pdf
powermon/protocols/docs/DALY-Daly_RS485_UART_Protocol.pdf
powermon/protocols/docs/DALY-UART_485_Communications_Protocol_V1.2.pdf
powermon-1.0.18.dist-info/LICENSE
powermon-1.0.18.dist-info/METADATA
powermon-1.0.18.dist-info/WHEEL
powermon-1.0.18.dist-info/entry_points.txt
powermon-1.0.18.dist-info/RECORD
