Metadata-Version: 2.1
Name: powermon
Version: 1.0.18
Summary: Package to communicate with Solar inverters and BMSs
Home-page: https://github.com/jblance/powermon
Author: John Blance
Requires-Python: >=3.11,<3.13
Classifier: Programming Language :: Python :: 3
Classifier: Programming Language :: Python :: 3.11
Classifier: Programming Language :: Python :: 3.12
Provides-Extra: api
Provides-Extra: ble
Provides-Extra: dev
Provides-Extra: modbus
Provides-Extra: systemd
Requires-Dist: PyYAML (>=6)
Requires-Dist: autodocsumm (>=0.2.13,<0.3.0) ; extra == "dev"
Requires-Dist: bleak (>=0.21.1) ; extra == "ble" or extra == "dev"
Requires-Dist: construct (>=2.10.70,<3.0.0)
Requires-Dist: cysystemd (>=1.6.0) ; extra == "systemd"
Requires-Dist: dateparser (>=1.2.0,<2.0.0)
Requires-Dist: deepdiff (>=8.0.1,<9.0.0)
Requires-Dist: fastapi (>=0.68.0) ; extra == "api"
Requires-Dist: fastapi-mqtt (>=1.1) ; extra == "api"
Requires-Dist: jinja2 (>=3.1.3,<4.0.0) ; extra == "api"
Requires-Dist: paho-mqtt (>=1.6,<2.0.0)
Requires-Dist: pyaml-env (>=1.2.1,<2.0.0)
Requires-Dist: pycryptodome (>=3.20.0,<4.0.0) ; extra == "ble" or extra == "dev"
Requires-Dist: pydantic (>=1.8.0)
Requires-Dist: pymodbus (>=3.6.4,<4.0.0) ; extra == "modbus"
Requires-Dist: pyserial (>3)
Requires-Dist: requests (>=2.31.0) ; extra == "api"
Requires-Dist: ruamel-yaml (>=0.18.6,<0.19.0)
Requires-Dist: sphinx (>=8.0.2,<9.0.0) ; extra == "dev"
Requires-Dist: sphinx-press-theme (>=0.9.1,<0.10.0) ; extra == "dev"
Requires-Dist: sqlalchemy (>=2.0.15,<3.0.0) ; extra == "api"
Requires-Dist: tenacity (>=9.0.0,<10.0.0)
Requires-Dist: uvicorn (>=0.15.0) ; extra == "api"
Project-URL: Bug Tracker, https://github.com/jblance/powermon/issues
Project-URL: Documentation, https://jblance.github.io/powermon/index.html
Project-URL: Repository, https://github.com/jblance/powermon
